LICENSE
MANIFEST.in
README.rst
setup.py
jsonapi/__init__.py
jsonapi/version.py
jsonapi/asyncio/__init__.py
jsonapi/asyncio/api.py
jsonapi/asyncio/database.py
jsonapi/asyncio/serializer.py
jsonapi/asyncio/handler/__init__.py
jsonapi/asyncio/handler/base.py
jsonapi/asyncio/handler/collection.py
jsonapi/asyncio/handler/related.py
jsonapi/asyncio/handler/relationship.py
jsonapi/asyncio/handler/resource.py
jsonapi/base/__init__.py
jsonapi/base/api.py
jsonapi/base/database.py
jsonapi/base/errors.py
jsonapi/base/pagination.py
jsonapi/base/request.py
jsonapi/base/response.py
jsonapi/base/schema.py
jsonapi/base/serializer.py
jsonapi/base/utilities.py
jsonapi/base/validators.py
jsonapi/base/handler/__init__.py
jsonapi/base/handler/base.py
jsonapi/base/handler/collection.py
jsonapi/base/handler/related.py
jsonapi/base/handler/relationship.py
jsonapi/base/handler/resource.py
jsonapi/flask/__init__.py
jsonapi/flask/api.py
jsonapi/marker/__init__.py
jsonapi/marker/method.py
jsonapi/marker/property.py
jsonapi/mongoengine/__init__.py
jsonapi/mongoengine/database.py
jsonapi/mongoengine/schema.py
jsonapi/motorengine/__init__.py
jsonapi/motorengine/database.py
jsonapi/motorengine/schema.py
jsonapi/sqlalchemy/__init__.py
jsonapi/sqlalchemy/database.py
jsonapi/sqlalchemy/schema.py
jsonapi/tornado/__init__.py
jsonapi/tornado/api.py
py_jsonapi.egg-info/PKG-INFO
py_jsonapi.egg-info/SOURCES.txt
py_jsonapi.egg-info/dependency_links.txt
py_jsonapi.egg-info/requires.txt
py_jsonapi.egg-info/top_level.txt