Metadata-Version: 1.1
Name: py-jsonapi
Version: 0.2.5b0
Summary: A toolkit for building a JSONapi
Home-page: https://github.com/benediktschmitt/py-jsonapi
Author: Benedikt Schmitt
Author-email: benedikt@benediktschmitt.de
License: The MIT License (MIT)
